.gitignore
LICENSE
README.md
rplidar.py
setup.py
docs/Makefile
docs/conf.py
docs/index.rst
docs/requirements.txt
examples/animate.py
examples/measure_speed.py
examples/record_measurments.py
examples/record_scans.py
rplidar_sharpattack.egg-info/PKG-INFO
rplidar_sharpattack.egg-info/SOURCES.txt
rplidar_sharpattack.egg-info/dependency_links.txt
rplidar_sharpattack.egg-info/requires.txt
rplidar_sharpattack.egg-info/top_level.txt
rplidar_sharpattack.egg-info/zip-safe